genevieve/__init__.py
test/__init__.py
test/test_genevieve.py
genevieve-1.0.3.dist-info/METADATA
genevieve-1.0.3.dist-info/WHEEL
genevieve-1.0.3.dist-info/entry_points.txt
genevieve-1.0.3.dist-info/top_level.txt
genevieve-1.0.3.dist-info/RECORD
