Metadata-Version: 2.1
Name: genevieve
Version: 1.0.3
Summary: Generates env variable scripts for Bash and PowerShell
Home-page: https://github.com/kjczarne/genevieve
Author: Product Testing Technica Engineering GmbH
Author-email: kjczarne@gmail.com
License: MIT
Keywords: environment variables,bash,powershell,windows,linux,osx
Platform: UNKNOWN
Classifier: License :: OSI Approved :: MIT License
Classifier: Programming Language :: Python :: 3
Classifier: Programming Language :: Python :: 3.7
Requires-Python: >=3.7
Requires-Dist: pyyaml
Requires-Dist: dataclasses-jsonschema
Provides-Extra: dev
Requires-Dist: pdoc ; extra == 'dev'
Requires-Dist: flake8 ; extra == 'dev'
Requires-Dist: twine ; extra == 'dev'
Requires-Dist: setuptools ; extra == 'dev'
Requires-Dist: autopep8 ; extra == 'dev'
